strmprivacy_io_strmprivacy_schemas_demo_v1/__init__.py
strmprivacy_io_strmprivacy_schemas_demo_v1/schema.avsc
strmprivacy_io_strmprivacy_schemas_demo_v1/schema_classes.py
strmprivacy_io_strmprivacy_schemas_demo_v1/io/__init__.py
strmprivacy_io_strmprivacy_schemas_demo_v1/io/strmprivacy/__init__.py
strmprivacy_io_strmprivacy_schemas_demo_v1/io/strmprivacy/schemas/__init__.py
strmprivacy_io_strmprivacy_schemas_demo_v1/io/strmprivacy/schemas/demo/__init__.py
strmprivacy_io_strmprivacy_schemas_demo_v1/io/strmprivacy/schemas/demo/v1/__init__.py
strmprivacy_schemas_demo_avro-1.0.2.post1.dist-info/METADATA
strmprivacy_schemas_demo_avro-1.0.2.post1.dist-info/WHEEL
strmprivacy_schemas_demo_avro-1.0.2.post1.dist-info/top_level.txt
strmprivacy_schemas_demo_avro-1.0.2.post1.dist-info/RECORD
