Metadata-Version: 2.1
Name: strmprivacy-schemas-demo-avro
Version: 1.0.2.post1
Summary: Python classes for demo
Home-page: UNKNOWN
Author: Stream Machine B.V.
Author-email: apis@strmprivacy.io
License: UNKNOWN
Keywords: strmprivacy api client driver schema
Platform: UNKNOWN
Classifier: Programming Language :: Python :: 3.6
Classifier: Programming Language :: Python :: 3.7
Classifier: Programming Language :: Python :: 3.8
Classifier: Programming Language :: Python :: 3.9
Classifier: Intended Audience :: Developers
Classifier: Operating System :: OS Independent
Classifier: Topic :: Internet :: WWW/HTTP
Requires-Python: >=3.6
Requires-Dist: avro-gen (==0.3.0)
Requires-Dist: tzlocal (==2.1)
